weather_yq_c/__init__.py
weather_yq_c/mcp.py
weather_yq_c-0.1.0.dist-info/METADATA
weather_yq_c-0.1.0.dist-info/WHEEL
weather_yq_c-0.1.0.dist-info/entry_points.txt
weather_yq_c-0.1.0.dist-info/RECORD
